measure_space_api/__init__.py
measure_space_api/constants.py
measure_space_api/main.py
measure_space_api-0.1.3.dist-info/METADATA
measure_space_api-0.1.3.dist-info/WHEEL
measure_space_api-0.1.3.dist-info/entry_points.txt
measure_space_api-0.1.3.dist-info/licenses/LICENSE
measure_space_api-0.1.3.dist-info/RECORD
