Metadata-Version: 2.4
Name: measure-space-api
Version: 0.1.3
Summary: A Python wrapper for the APIs of MeasureSpace.io
Author-email: Measure Space <support@measurespace.io>
License-File: LICENSE
Requires-Python: >=3.10
Requires-Dist: pandas
Requires-Dist: python-dotenv
Requires-Dist: requests
